fgivenx/__init__.py
fgivenx/_utils.py
fgivenx/dkl.py
fgivenx/drivers.py
fgivenx/io.py
fgivenx/mass.py
fgivenx/parallel.py
fgivenx/plot.py
fgivenx/samples.py
fgivenx/test/__init__.py
fgivenx/test/test__utils.py
fgivenx/test/test_dkl.py
fgivenx/test/test_drivers.py
fgivenx/test/test_io.py
fgivenx/test/test_mass.py
fgivenx/test/test_parallel.py
fgivenx/test/test_plot.py
fgivenx/test/test_samples.py
fgivenx/test/baseline_images/test_drivers/fgivenx.pdf
fgivenx/test/baseline_images/test_plot/plot.pdf
fgivenx/test/baseline_images/test_plot/plot_lines.pdf
fgivenx/test/baseline_images/test_plot/plot_lines_downsample.pdf
fgivenx/test/baseline_images/test_plot/plot_lines_no_ax.pdf
fgivenx/test/baseline_images/test_plot/plot_no_ax.pdf
fgivenx/test/baseline_images/test_plot/plot_nolines.pdf
fgivenx/test/baseline_images/test_plot/plot_rasterize.pdf
fgivenx/test/baseline_images/test_plot/plot_smooth.pdf
fgivenx-2.4.2.dist-info/LICENSE.txt
fgivenx-2.4.2.dist-info/METADATA
fgivenx-2.4.2.dist-info/WHEEL
fgivenx-2.4.2.dist-info/top_level.txt
fgivenx-2.4.2.dist-info/RECORD
