Metadata-Version: 2.1
Name: fgivenx
Version: 2.4.2
Summary: fgivenx: Functional Posterior Plotter
Home-page: https://github.com/fgivenx/fgivenx
Author: Will Handley
Author-email: wh260@cam.ac.uk
License: MIT
Classifier: Development Status :: 5 - Production/Stable
Classifier: Intended Audience :: Developers
Classifier: Intended Audience :: Science/Research
Classifier: Natural Language :: English
Classifier: License :: OSI Approved :: MIT License
Classifier: Programming Language :: Python :: 2.7
Classifier: Programming Language :: Python :: 3.4
Classifier: Programming Language :: Python :: 3.5
Classifier: Programming Language :: Python :: 3.6
Classifier: Topic :: Scientific/Engineering
Classifier: Topic :: Scientific/Engineering :: Astronomy
Classifier: Topic :: Scientific/Engineering :: Physics
Classifier: Topic :: Scientific/Engineering :: Visualization
Classifier: Topic :: Scientific/Engineering :: Information Analysis
Classifier: Topic :: Scientific/Engineering :: Mathematics
License-File: LICENSE.txt
Requires-Dist: matplotlib
Requires-Dist: numpy
Requires-Dist: scipy
Provides-Extra: docs
Requires-Dist: sphinx ; extra == 'docs'
Requires-Dist: sphinx-rtd-theme ; extra == 'docs'
Requires-Dist: numpydoc ; extra == 'docs'
Provides-Extra: getdist_chains
Requires-Dist: getdist ; extra == 'getdist_chains'
Provides-Extra: parallel
Requires-Dist: joblib ; extra == 'parallel'
Provides-Extra: progress_bar
Requires-Dist: tqdm ; extra == 'progress_bar'
